cargparse/__init__.py
cargparse/base.py
cargparse/type.py
cargparse/utils.py
cargparse-0.0.9.dist-info/LICENSE
cargparse-0.0.9.dist-info/METADATA
cargparse-0.0.9.dist-info/WHEEL
cargparse-0.0.9.dist-info/top_level.txt
cargparse-0.0.9.dist-info/RECORD
