Metadata-Version: 2.1
Name: cargparse
Version: 0.0.9
Summary: Configuration file parsing with argparse.
Author: Eric DeMattos
Project-URL: Homepage, https://github.com/edemattos/cargparse
Project-URL: Bug Tracker, https://github.com/edemattos/cargparse/issues
Classifier: Programming Language :: Python :: 3 :: Only
Classifier: Programming Language :: Python :: 3
Classifier: Programming Language :: Python :: 3.7
Classifier: Programming Language :: Python :: 3.8
Classifier: Programming Language :: Python :: 3.9
Classifier: Programming Language :: Python :: 3.10
Classifier: License :: OSI Approved :: MIT License
Classifier: Operating System :: OS Independent
Requires-Python: >=3.7
License-File: LICENSE
Requires-Dist: pyyaml
Requires-Dist: tomli
